{
  "name": "Bruce Peters",
  "age": 45,
  "address": {
    "street": "Evitur Center",
    "city": "Omcado",
    "state": "MD",
    "zip": "60195"
  },
  "contact": {
    "phone": "(419) 844-2441",
    "servicePhone": "800231813"
  },
  "birthday": "2002-10-17T04:10:32.921Z",
  "ip": "150.5.73.71",
  "foo": "bar",
  "profile": {
    "about": "Lepibe vef izba ficap puj pow mo ne dujo wo velwepke odicopi woroz ogigen ker ruemi azfi zefuj. Rofewu ba mesnu burcuw upiedzo apesi ipcan to nofab novnosa pugihos movo vam ki mev epobeci dej usa. Ipje sirfefpeh fejbarez dopi afe emzalufe irodur se ba le fus vu davajlo. Urhube ma morulip rasudew okuciw donvirij akucan rat ga daz fuwbe avo nupnubhet adi hopiruh jucviiv nipirbop fulwitka. Jur ajanahad kabiluk hetaj boeni ov cujjijiz mav vulif mub ej vaenad tunofcel.",
    "bio": "Luacera lajifij subvuhum ujvorziz kettur jiztef dibe abbif ko povra rimore ceanevu colejopup gesgo. Gesne felsecu bel jiga divi gupan reutwe cabbindup bulwiftoh so nunaher pibhepote ad. Binu pi atwe le uj det juc ja gozjakvo debokif itiatutol dipuwe tilraek luifo loavu ku ig. Adzosvi jel lu geada nifbina ekdo ufiko gisu tag zalpina zu uwoawmo emsic bedohe ta jinor lezoivi pilisda. Megsimve momkob sewaul nazifig do nup leh coni ibujuc vowonka fagzawu ti luv. Idaireus wit hurgo ja halo govod rabni hatodano ronzuobi mat ka woutpe ciiw. Zaszunu un hispuzco dov juge ico evugiwsob tuw nesij bunguv vig eznuw fo."
  },
  "apiKey": "9c80dca121f589b5745cf78cf67d946866a80813cfb1f28972586956dba9cdbb",
  "currency": {
    "code": "GGP",
    "name": "Guernsey Pound"
  }
}