{
  "name": "Victoria Morris",
  "age": 25,
  "address": {
    "street": "Rueke Square",
    "city": "Ujwulga",
    "state": "WI",
    "zip": "08410"
  },
  "contact": {
    "phone": "(469) 712-1340",
    "servicePhone": "800632814"
  },
  "birthday": "1978-06-20T22:03:24.790Z",
  "ip": "173.213.151.219",
  "foo": "bar",
  "profile": {
    "about": "Piw olneckav etrared seca darakedeh geumsoz bafvudu hawdo rilzom azouzkub sulemoh go anamupup pipocupaf ko uv. Kunili suhzu is feflil cijotez numit gugi huwigez bijake kahreunu tehbip fojrumup. Li covirji sefelgik javjelu ruve son sutvesu lifkaz laj wewi ece nuviobu. Wumih on eb liwkic fe eh foja af uk somivi seji johkak ujeli zanasca nesumeri alaputu.",
    "bio": "Owajiasi mone cuvri pumur giweb pagir zuvrek kibzah asatosu hoiwzoj mivmuim bikzuic gawap. Zili kubu kodilif vumusfir henzawop jo urojer goutca somco pipwofu tapve ufgaz ohiepri pigwazbe. Letahnot ezeeminah boz ken kuvkuzso raafa as tocbowbe kaf joggim jezpauko peb torej jad rape palfa."
  },
  "apiKey": "bf6fb04eff9e41659fd3a6184d4e009fca2280e05778cb03a0f756a4868e95ea",
  "currency": {
    "code": "RWF",
    "name": "Rwanda Franc"
  }
}