{
  "name": "Walter Bates",
  "age": 25,
  "address": {
    "street": "Uplib View",
    "city": "Subkemmim",
    "state": "IA",
    "zip": "70850"
  },
  "contact": {
    "phone": "(955) 381-2073",
    "servicePhone": "800614912"
  },
  "birthday": "1971-02-26T10:40:51.522Z",
  "ip": "244.184.230.47",
  "foo": "bar",
  "profile": {
    "about": "Cirwa wuigwud vu niuvoza od esudoc saja vac ate muna amcapo kukke ijoleel. Rouhonef pocham afa da keddon muhjon sacvo fumopij jujeuwe micoba ere zu mita. Mudu mivaf onlefhob sibac tod logtunwa atiggu hetul mi fezaz tehlubwe dakzilwak ofepewam weabec das. Ege boflom tucnewib ehe abdod fianigi gohratoz tewadec le bobujoj wowigfug hobfa al. Jeren joz rad zofcore bokko puluj alutojpi piv fapanha zife zeven op vegi egi ko. Nader hojowe owu zujnowu aju hejelfip mi mekwa ascu avitas um rogupucic lut nusfu useri loj. Dajiw lucub cun beceid upoiv uvlalapa nagjoni zeapce girdup bacra wab ifo uve kol zurosaf zubof.",
    "bio": "Cippowuh gokbaja bikho jac ocu fe wemiwak ra it coraife sel tunfefu kazoz. Kuj gewhej gi wazusduk zog fiti mukhavse vu huziwdud zime giriwel hilijcos ceili navuf canile zeguto icamuv. Nawhenij wi fab tantefsu ho ahuvodnih su kaja cabogo wiz apkise nafu sad re rardeofe miedisuj joopcaz. Vi sam misegbij koel zu seben ceflemat gebme ulviz kem sihu kurfe pimuk go nadpese botisan su. Gaz tesazufuj ata zuwzuhle co ih ja ejo fed ad un lobcu. Bivavhu ruv su gitittek raham uhodo ejafaic bi tarebfe lupbegca fa peswawa co mih zaj isbudin. Tu bezukufi sajukleb bunubaigu gij puek ha zebe gaco ri co jezzu tom."
  },
  "apiKey": "6d9b094195271ad3f9a596e5c7459caf484516e89bfc0bd0eab3f2f5a3441310",
  "currency": {
    "code": "THB",
    "name": "Thailand Baht"
  }
}